quaternion_djs/__init__.py
quaternion_djs/quaternion.py
quaternion_djs/tests/__init__.py
quaternion_djs/tests/test_quaternion.py
quaternion_djs-1.1.0.dist-info/LICENSE
quaternion_djs-1.1.0.dist-info/METADATA
quaternion_djs-1.1.0.dist-info/WHEEL
quaternion_djs-1.1.0.dist-info/RECORD
