Metadata-Version: 2.1
Name: quaternion_djs
Version: 1.1.0
Summary: A package for using quaternions
Home-page: https://github.com/DrJStrudwick/Quaternion
License: MIT
Author: James Strudwick
Author-email: James.Strudwick@ibm.com
Requires-Python: >=3.10,<4.0
Classifier: License :: OSI Approved :: MIT License
Classifier: Programming Language :: Python :: 3
Classifier: Programming Language :: Python :: 3.10
Classifier: Programming Language :: Python :: 3.11
Classifier: Programming Language :: Python :: 3.12
Project-URL: Changelog, https://github.com/DrJStrudwick/Quaternion/blob/main/CHANGELOG.md
Project-URL: Documentation, https://quaternion-djs.readthedocs.io/en/latest/
Project-URL: Issues, https://github.com/DrJStrudwick/Quaternion/issues
Project-URL: Repository, https://github.com/DrJStrudwick/Quaternion
